shinigami_cli-0.1.4.data/scripts/cli.py
src/cli.py
shinigami_cli-0.1.4.dist-info/LICENSE
shinigami_cli-0.1.4.dist-info/METADATA
shinigami_cli-0.1.4.dist-info/WHEEL
shinigami_cli-0.1.4.dist-info/entry_points.txt
shinigami_cli-0.1.4.dist-info/top_level.txt
shinigami_cli-0.1.4.dist-info/RECORD
