Metadata-Version: 2.1
Name: shinigami-cli
Version: 0.1.4
Summary: Basic CLI showing off the Shinigami library.
Home-page: https://github.com/shinigamilib/cli
Author: azazelm3dj3d
Classifier: Programming Language :: Python :: 3
Classifier: License :: OSI Approved :: BSD License
Classifier: Operating System :: OS Independent
Requires-Python: >=3.6
License-File: LICENSE
Requires-Dist: argparse
Requires-Dist: shinigami
